llm_mathjudger-0.2.1.dist-info/METADATA
llm_mathjudger-0.2.1.dist-info/WHEEL
llm_mathjudger-0.2.1.dist-info/entry_points.txt
llm_mathjudger/.DS_Store
llm_mathjudger/__init__.py
llm_mathjudger/data/.DS_Store
llm_mathjudger/data/4o_correct/.DS_Store
llm_mathjudger/data/4o_correct/test.jsonl
llm_mathjudger/data/4o_wrong/.DS_Store
llm_mathjudger/data/4o_wrong/test.jsonl
llm_mathjudger/data/asdiv/test.jsonl
llm_mathjudger/data/gsm8k/test.jsonl
llm_mathjudger/data/gsm8k/train.jsonl
llm_mathjudger/data/gsm_hard/test.jsonl
llm_mathjudger/data/hungarian_exam/README.md
llm_mathjudger/data/hungarian_exam/test.jsonl
llm_mathjudger/data/math/test.jsonl
llm_mathjudger/data/math/train.jsonl
llm_mathjudger/data/math_oai/test.jsonl
llm_mathjudger/data/math_oai_correct/.DS_Store
llm_mathjudger/data/math_oai_correct/test.jsonl
llm_mathjudger/data/math_oai_wrong/test.jsonl
llm_mathjudger/data/math_oai_wrong_50/test.jsonl
llm_mathjudger/data/mathqa/test.jsonl
llm_mathjudger/data/mawps/addsub.jsonl
llm_mathjudger/data/mawps/multiarith.jsonl
llm_mathjudger/data/mawps/singleeq.jsonl
llm_mathjudger/data/mawps/singleop.jsonl
llm_mathjudger/data/mawps/test.jsonl
llm_mathjudger/data/mmlu_stem/test.jsonl
llm_mathjudger/data/ocw/README.md
llm_mathjudger/data/ocw/test.jsonl
llm_mathjudger/data/sat_math/test.jsonl
llm_mathjudger/data/svamp/test.jsonl
llm_mathjudger/data/tabmwp/test.jsonl
llm_mathjudger/grader.py
llm_mathjudger/parser.py
llm_mathjudger/prompts/cot/gsm8k.md
llm_mathjudger/prompts/cot/math.md
llm_mathjudger/prompts/cot/math_8shot.md
llm_mathjudger/prompts/cot/mathqa.md
llm_mathjudger/prompts/cot/minerva_math.md
llm_mathjudger/prompts/cot/mmlu_stem.md
llm_mathjudger/prompts/pal/gsm8k.md
llm_mathjudger/prompts/pal/math.md
llm_mathjudger/prompts/tora/gsm8k.md
llm_mathjudger/prompts/tora/math.md
llm_mathjudger/python_executor.py
llm_mathjudger/trajectory.py
llm_mathjudger/utils.py
llm_mathjudger/verify.py
llm_mathjudger-0.2.1.dist-info/RECORD
