Metadata-Version: 2.1
Name: llm_mathjudger
Version: 0.2.1
Summary: A sitreamlined version of "LLM-Math" that judges the math solutions of LLMs.
Author-Email: Haoxiang Sun <hxiang.sun@gmail.com>
License: MIT
Requires-Python: >=3.10
Requires-Dist: word2number
Requires-Dist: antlr4-python3-runtime==4.11.1
Requires-Dist: Pebble
Requires-Dist: timeout-decorator
Requires-Dist: latex2sympy2-llmmath==1.9.1
Requires-Dist: sympy==1.12
Requires-Dist: regex
Requires-Dist: python-dateutil
Requires-Dist: multiprocess
